cleanmypc/__init__.py
cleanmypc/cache.py
cleanmypc/temp.py
cleanmypc-1.0.3.dist-info/licenses/LICENSE
cleanmypc-1.0.3.dist-info/METADATA
cleanmypc-1.0.3.dist-info/WHEEL
cleanmypc-1.0.3.dist-info/top_level.txt
cleanmypc-1.0.3.dist-info/RECORD
