Metadata-Version: 2.4
Name: cleanmypc
Version: 1.0.3
Summary: A Python library to clean cache and temporary files from your PC
Home-page: https://github.com/Mandel123e/cleanmypc
Author: Mandel123e
Author-email: Mandel123e <mandel123e@gmail.com>
License: MIT
Project-URL: Homepage, https://github.com/Mandel123e/cleanmypc
Project-URL: Repository, https://github.com/Mandel123e/cleanmypc
Keywords: clean,cache,temporary files,pc,python
Requires-Python: >=3.6
License-File: LICENSE
Requires-Dist: send2trash
Dynamic: author
Dynamic: home-page
Dynamic: license-file
Dynamic: requires-python
